GRFlood/__init__.py
GRFlood-1.0.0.dist-info/LICENSE.txt
GRFlood-1.0.0.dist-info/METADATA
GRFlood-1.0.0.dist-info/WHEEL
GRFlood-1.0.0.dist-info/top_level.txt
GRFlood-1.0.0.dist-info/RECORD
