Metadata-Version: 2.1
Name: GRFlood
Version: 1.0.0
Summary: A small package for flood forecasting
Home-page: https://github.com/pypa/sampleproject
Author: AMIRA AYOUB
Author-email: ayoub.amira1998@gmail.com
License: UNKNOWN
Project-URL: Bug Tracker, https://github.com/pypa/sampleproject/issues
Platform: UNKNOWN
Classifier: Programming Language :: Python :: 3
Classifier: License :: OSI Approved :: MIT License
Classifier: Operating System :: OS Independent
Requires-Python: >=3.6
